setup.py
spyte/__init__.py
spyte/exceptions.py
spyte/executor.py
spyte/logger.py
spyte/threads.py
spyte.egg-info/PKG-INFO
spyte.egg-info/SOURCES.txt
spyte.egg-info/dependency_links.txt
spyte.egg-info/top_level.txt