Metadata-Version: 1.1
Name: spyte
Version: 0.0.2
Summary: Simple Python Test Engine
Home-page: UNKNOWN
Author: Sean Jennings
Author-email: UNKNOWN
License: MIT
Keywords: test executive development
Platform: UNKNOWN
Classifier: Development Status :: 3 - Alpha
Classifier: Intended Audience :: Developers
Classifier: Topic :: Software Development :: Quality Assurance
Classifier: Programming Language :: Python :: 2.7
